storedict/__init__.py
storedict/storedict.py
storedict/tests.py
storedict-0.0.16.dist-info/METADATA
storedict-0.0.16.dist-info/WHEEL
storedict-0.0.16.dist-info/top_level.txt
storedict-0.0.16.dist-info/RECORD
